{
    "id": null,
    "metadata": {
        "source": "../data/layout-parser-paper.pdf",
        "is_extracted": "true",
        "coordinates": {
            "points": [
                [
                    471.4206848144531,
                    716.1183388888885
                ],
                [
                    471.4206848144531,
                    863.0947265625
                ],
                [
                    1674.0748614123202,
                    863.0947265625
                ],
                [
                    1674.0748614123202,
                    716.1183388888885
                ]
            ],
            "system": "PixelSpace",
            "layout_width": 2125,
            "layout_height": 2750
        },
        "filetype": "application/pdf",
        "languages": [
            "eng"
        ],
        "page_number": 16,
        "filename": "layout-parser-paper.pdf",
        "parent_id": "2125d675311c00e01a24886e8a603ee1",
        "category": "ListItem",
        "element_id": "c81432ac5c76b82c1ccd93d0a3ee15b1"
    },
    "page_content": "[26] Prasad, D., Gadpal, A., Kapadni, K., Visave, M., Sultanpure, K.: Cascadetabnet: An approach for end to end table detection and structure recognition from image- based documents. In: Proceedings of the IEEE/CVF Conference on Computer Vision and Pattern Recognition Workshops. pp. 572–573 (2020)",
    "type": "Document"
}